fastapi_paseto_auth/__init__.py
fastapi_paseto_auth/auth_config.py
fastapi_paseto_auth/auth_paseto.py
fastapi_paseto_auth/config.py
fastapi_paseto_auth/exceptions.py
fastapi_paseto_auth-0.6.0.dist-info/LICENSE
fastapi_paseto_auth-0.6.0.dist-info/WHEEL
fastapi_paseto_auth-0.6.0.dist-info/METADATA
fastapi_paseto_auth-0.6.0.dist-info/RECORD
