Metadata-Version: 2.1
Name: fastapi-paseto-auth
Version: 0.6.0
Summary: FastAPI extension that provides PASETO Auth support
Home-page: https://github.com/Chloe-ko/fastapi-paseto-auth
Author: Neneko
Author-email: fastapi@nyu.moe
Requires-Python: >=3.10
Classifier: Environment :: Web Environment
Classifier: Intended Audience :: Developers
Classifier: Programming Language :: Python :: 3
Classifier: Programming Language :: Python :: 3.10
Classifier: License :: OSI Approved :: MIT License
Classifier: Operating System :: OS Independent
Classifier: Topic :: Internet :: WWW/HTTP :: Dynamic Content
Classifier: Topic :: Software Development :: Libraries :: Python Modules
Requires-Dist: fastapi>=0.65.3,<=0.85.0
Requires-Dist: pyseto>=1.6.9,<=1.6.10
Requires-Dist: pydantic>=1.9.1,<=1.10.2
Requires-Dist: uvicorn>=0.11.5 ; extra == "dev"
Requires-Dist: mkdocs>=1.1.2,<2.0.0 ; extra == "doc"
Requires-Dist: mkdocs-material>=8.3.9,<9.0.0 ; extra == "doc"
Requires-Dist: markdown-include>=0.7.0,<0.8.0 ; extra == "doc"
Requires-Dist: pytest==7.1.3 ; extra == "test"
Requires-Dist: pytest-cov==3.0.0 ; extra == "test"
Requires-Dist: coveralls==3.3.1 ; extra == "test"
Project-URL: Documentation, https://chloe-ko.github.io/fastapi-paseto-auth/
Provides-Extra: dev
Provides-Extra: doc
Provides-Extra: test
